{
  "main": {
    "kea": {
      "identity": {
        "version": {
          "_number": "$Revision: 12307 $",
          "_cldrVersion": "29"
        },
        "language": "kea"
      },
      "units": {
        "long": {
          "per": {
            "compoundUnitPattern": "{0}/{1}"
          },
          "acceleration-g-force": {
            "displayName": "forsa G",
            "unitPattern-count-other": "{0} forsa G"
          },
          "acceleration-meter-per-second-squared": {
            "displayName": "métru pur sigundu kuadradu",
            "unitPattern-count-other": "{0} métru pur sigundu kuadradu"
          },
          "angle-revolution": {
            "displayName": "rev",
            "unitPattern-count-other": "{0} rev"
          },
          "angle-radian": {
            "displayName": "radianu",
            "unitPattern-count-other": "{0} radianu"
          },
          "angle-degree": {
            "displayName": "grau",
            "unitPattern-count-other": "{0} grau"
          },
          "angle-arc-minute": {
            "displayName": "arcmin",
            "unitPattern-count-other": "{0}′"
          },
          "angle-arc-second": {
            "displayName": "arcsec",
            "unitPattern-count-other": "{0}″"
          },
          "area-square-kilometer": {
            "displayName": "kilómetru kuadradu",
            "unitPattern-count-other": "{0} kilómetru kuadradu"
          },
          "area-hectare": {
            "displayName": "ektar",
            "unitPattern-count-other": "{0} ektar"
          },
          "area-square-meter": {
            "displayName": "métru kuadradu",
            "unitPattern-count-other": "{0} métru kuadradu",
            "perUnitPattern": "{0}/m²"
          },
          "area-square-centimeter": {
            "displayName": "sentímetru kuadradu",
            "unitPattern-count-other": "{0} sentímetru kuadradu",
            "perUnitPattern": "{0}/cm²"
          },
          "area-square-mile": {
            "displayName": "milha kuadradu",
            "unitPattern-count-other": "{0} milha kuadradu"
          },
          "area-acre": {
            "displayName": "ákri",
            "unitPattern-count-other": "{0} ákri"
          },
          "area-square-yard": {
            "displayName": "jarda kuadradu",
            "unitPattern-count-other": "{0} jarda kuadradu"
          },
          "area-square-foot": {
            "displayName": "pé kuadradu",
            "unitPattern-count-other": "{0} pé kuadradu"
          },
          "area-square-inch": {
            "displayName": "pulegada kuadradu",
            "unitPattern-count-other": "{0} pulegada kuadradu",
            "perUnitPattern": "{0}/in²"
          },
          "concentr-karat": {
            "displayName": "kilati",
            "unitPattern-count-other": "{0} kilati"
          },
          "concentr-milligram-per-deciliter": {
            "displayName": "mg/dL",
            "unitPattern-count-other": "{0} mg/dL"
          },
          "concentr-millimole-per-liter": {
            "displayName": "mmol/L",
            "unitPattern-count-other": "{0} mmol/L"
          },
          "concentr-part-per-million": {
            "displayName": "ppm",
            "unitPattern-count-other": "{0} ppm"
          },
          "consumption-liter-per-kilometer": {
            "displayName": "litru pur kilómetru",
            "unitPattern-count-other": "{0} litru pur kilómetru"
          },
          "consumption-liter-per-100kilometers": {
            "displayName": "L/100km",
            "unitPattern-count-other": "{0} L/100km"
          },
          "consumption-mile-per-gallon": {
            "displayName": "milha pur galãu",
            "unitPattern-count-other": "{0} milha pur galãu"
          },
          "consumption-mile-per-gallon-imperial": {
            "displayName": "mpg Imp.",
            "unitPattern-count-other": "{0} mpg Imp."
          },
          "digital-terabyte": {
            "displayName": "terabyte",
            "unitPattern-count-other": "{0} terabyte"
          },
          "digital-terabit": {
            "displayName": "terabit",
            "unitPattern-count-other": "{0} terabit"
          },
          "digital-gigabyte": {
            "displayName": "jigabyte",
            "unitPattern-count-other": "{0} jigabyte"
          },
          "digital-gigabit": {
            "displayName": "jigabit",
            "unitPattern-count-other": "{0} jigabit"
          },
          "digital-megabyte": {
            "displayName": "megabyte",
            "unitPattern-count-other": "{0} megabyte"
          },
          "digital-megabit": {
            "displayName": "megabit",
            "unitPattern-count-other": "{0} megabit"
          },
          "digital-kilobyte": {
            "displayName": "kilobyte",
            "unitPattern-count-other": "{0} kilobyte"
          },
          "digital-kilobit": {
            "displayName": "kilobit",
            "unitPattern-count-other": "{0} kilobit"
          },
          "digital-byte": {
            "displayName": "byte",
            "unitPattern-count-other": "{0} byte"
          },
          "digital-bit": {
            "displayName": "bit",
            "unitPattern-count-other": "{0} bit"
          },
          "duration-century": {
            "displayName": "c",
            "unitPattern-count-other": "{0} c"
          },
          "duration-year": {
            "displayName": "anu",
            "unitPattern-count-other": "{0} anu",
            "perUnitPattern": "{0}/y"
          },
          "duration-month": {
            "displayName": "mes",
            "unitPattern-count-other": "{0} mes",
            "perUnitPattern": "{0}/m"
          },
          "duration-week": {
            "displayName": "simana",
            "unitPattern-count-other": "{0} simana",
            "perUnitPattern": "{0}/w"
          },
          "duration-day": {
            "displayName": "dia",
            "unitPattern-count-other": "{0} dia",
            "perUnitPattern": "{0}/d"
          },
          "duration-hour": {
            "displayName": "ora",
            "unitPattern-count-other": "{0} ora",
            "perUnitPattern": "{0} pur ora"
          },
          "duration-minute": {
            "displayName": "minutu",
            "unitPattern-count-other": "{0} minutu",
            "perUnitPattern": "{0}/min"
          },
          "duration-second": {
            "displayName": "sigundu",
            "unitPattern-count-other": "{0} sigundu",
            "perUnitPattern": "{0} pur sigundu"
          },
          "duration-millisecond": {
            "displayName": "milisigundu",
            "unitPattern-count-other": "{0} milisigundu"
          },
          "duration-microsecond": {
            "displayName": "mikrosigundu",
            "unitPattern-count-other": "{0} mikrosigundu"
          },
          "duration-nanosecond": {
            "displayName": "nanosigundu",
            "unitPattern-count-other": "{0} nanosigundu"
          },
          "electric-ampere": {
            "displayName": "amp",
            "unitPattern-count-other": "{0} A"
          },
          "electric-milliampere": {
            "displayName": "mA",
            "unitPattern-count-other": "{0} mA"
          },
          "electric-ohm": {
            "displayName": "ohm",
            "unitPattern-count-other": "{0} Ω"
          },
          "electric-volt": {
            "displayName": "volt",
            "unitPattern-count-other": "{0} V"
          },
          "energy-kilocalorie": {
            "displayName": "kcal",
            "unitPattern-count-other": "{0} kcal"
          },
          "energy-calorie": {
            "displayName": "cal",
            "unitPattern-count-other": "{0} cal"
          },
          "energy-foodcalorie": {
            "displayName": "Cal",
            "unitPattern-count-other": "{0} Cal"
          },
          "energy-kilojoule": {
            "displayName": "kJ",
            "unitPattern-count-other": "{0} kJ"
          },
          "energy-joule": {
            "displayName": "joule",
            "unitPattern-count-other": "{0} J"
          },
          "energy-kilowatt-hour": {
            "displayName": "kWh",
            "unitPattern-count-other": "{0} kWh"
          },
          "frequency-gigahertz": {
            "displayName": "GHz",
            "unitPattern-count-other": "{0} GHz"
          },
          "frequency-megahertz": {
            "displayName": "MHz",
            "unitPattern-count-other": "{0} MHz"
          },
          "frequency-kilohertz": {
            "displayName": "kHz",
            "unitPattern-count-other": "{0} kHz"
          },
          "frequency-hertz": {
            "displayName": "Hz",
            "unitPattern-count-other": "{0} Hz"
          },
          "length-kilometer": {
            "displayName": "kilómetru",
            "unitPattern-count-other": "{0} kilómetru",
            "perUnitPattern": "{0}/km"
          },
          "length-meter": {
            "displayName": "métru",
            "unitPattern-count-other": "{0} métru",
            "perUnitPattern": "{0}/m"
          },
          "length-decimeter": {
            "displayName": "desímetru",
            "unitPattern-count-other": "{0} desímetru"
          },
          "length-centimeter": {
            "displayName": "sentímetru",
            "unitPattern-count-other": "{0} sentímetru",
            "perUnitPattern": "{0}/cm"
          },
          "length-millimeter": {
            "displayName": "milímetru",
            "unitPattern-count-other": "{0} milímetru"
          },
          "length-micrometer": {
            "displayName": "mikrómetru",
            "unitPattern-count-other": "{0} mikrómetru"
          },
          "length-nanometer": {
            "displayName": "nanómetru",
            "unitPattern-count-other": "{0} nanómetru"
          },
          "length-picometer": {
            "displayName": "pikómetru",
            "unitPattern-count-other": "{0} pikómetru"
          },
          "length-mile": {
            "displayName": "milha",
            "unitPattern-count-other": "{0} milha"
          },
          "length-yard": {
            "displayName": "jarda",
            "unitPattern-count-other": "{0} jarda"
          },
          "length-foot": {
            "displayName": "pé",
            "unitPattern-count-other": "{0} pé",
            "perUnitPattern": "{0}/ft"
          },
          "length-inch": {
            "displayName": "pulegada",
            "unitPattern-count-other": "{0} pulegada",
            "perUnitPattern": "{0}/in"
          },
          "length-parsec": {
            "displayName": "parsek",
            "unitPattern-count-other": "{0} parsek"
          },
          "length-light-year": {
            "displayName": "anu-lus",
            "unitPattern-count-other": "{0} anu-lus"
          },
          "length-astronomical-unit": {
            "displayName": "unidadi astronómiku",
            "unitPattern-count-other": "{0} unidadi astronómiku"
          },
          "length-furlong": {
            "displayName": "fur",
            "unitPattern-count-other": "{0} fur"
          },
          "length-fathom": {
            "displayName": "fm",
            "unitPattern-count-other": "{0} fm"
          },
          "length-nautical-mile": {
            "displayName": "milha náutiku",
            "unitPattern-count-other": "{0} milha náutiku"
          },
          "length-mile-scandinavian": {
            "displayName": "smi",
            "unitPattern-count-other": "{0} smi"
          },
          "light-lux": {
            "displayName": "lux",
            "unitPattern-count-other": "{0} lux"
          },
          "mass-metric-ton": {
            "displayName": "t",
            "unitPattern-count-other": "{0} t"
          },
          "mass-kilogram": {
            "displayName": "kg",
            "unitPattern-count-other": "{0} kg",
            "perUnitPattern": "{0}/kg"
          },
          "mass-gram": {
            "displayName": "gram",
            "unitPattern-count-other": "{0} g",
            "perUnitPattern": "{0}/g"
          },
          "mass-milligram": {
            "displayName": "mg",
            "unitPattern-count-other": "{0} mg"
          },
          "mass-microgram": {
            "displayName": "µg",
            "unitPattern-count-other": "{0} µg"
          },
          "mass-ton": {
            "displayName": "tn",
            "unitPattern-count-other": "{0} tn"
          },
          "mass-stone": {
            "displayName": "st",
            "unitPattern-count-other": "{0} st"
          },
          "mass-pound": {
            "displayName": "lb",
            "unitPattern-count-other": "{0} lb",
            "perUnitPattern": "{0}/lb"
          },
          "mass-ounce": {
            "displayName": "oz",
            "unitPattern-count-other": "{0} oz",
            "perUnitPattern": "{0}/oz"
          },
          "mass-ounce-troy": {
            "displayName": "oz t",
            "unitPattern-count-other": "{0} oz t"
          },
          "mass-carat": {
            "displayName": "CD",
            "unitPattern-count-other": "{0} CD"
          },
          "power-gigawatt": {
            "displayName": "GW",
            "unitPattern-count-other": "{0} GW"
          },
          "power-megawatt": {
            "displayName": "MW",
            "unitPattern-count-other": "{0} MW"
          },
          "power-kilowatt": {
            "displayName": "kW",
            "unitPattern-count-other": "{0} kW"
          },
          "power-watt": {
            "displayName": "watt",
            "unitPattern-count-other": "{0} W"
          },
          "power-milliwatt": {
            "displayName": "mW",
            "unitPattern-count-other": "{0} mW"
          },
          "power-horsepower": {
            "displayName": "hp",
            "unitPattern-count-other": "{0} hp"
          },
          "pressure-hectopascal": {
            "displayName": "hPa",
            "unitPattern-count-other": "{0} hPa"
          },
          "pressure-millimeter-of-mercury": {
            "displayName": "mm Hg",
            "unitPattern-count-other": "{0} mm Hg"
          },
          "pressure-pound-per-square-inch": {
            "displayName": "psi",
            "unitPattern-count-other": "{0} psi"
          },
          "pressure-inch-hg": {
            "displayName": "inHg",
            "unitPattern-count-other": "{0} inHg"
          },
          "pressure-millibar": {
            "displayName": "mbar",
            "unitPattern-count-other": "{0} mbar"
          },
          "speed-kilometer-per-hour": {
            "displayName": "kilómetru pur ora",
            "unitPattern-count-other": "{0} kilómetru pur ora"
          },
          "speed-meter-per-second": {
            "displayName": "métru pur sigundu",
            "unitPattern-count-other": "{0} métru pur sigundu"
          },
          "speed-mile-per-hour": {
            "displayName": "milha pur ora",
            "unitPattern-count-other": "{0} milha pur ora"
          },
          "speed-knot": {
            "displayName": "kn",
            "unitPattern-count-other": "{0} kn"
          },
          "temperature-generic": {
            "displayName": "°",
            "unitPattern-count-other": "{0}°"
          },
          "temperature-celsius": {
            "displayName": "°C",
            "unitPattern-count-other": "{0}°C"
          },
          "temperature-fahrenheit": {
            "displayName": "°F",
            "unitPattern-count-other": "{0}°F"
          },
          "temperature-kelvin": {
            "displayName": "K",
            "unitPattern-count-other": "{0} K"
          },
          "volume-cubic-kilometer": {
            "displayName": "kilómetru kúbiku",
            "unitPattern-count-other": "{0} kilómetru kúbiku"
          },
          "volume-cubic-meter": {
            "displayName": "métru kúbiku",
            "unitPattern-count-other": "{0} métru kúbiku",
            "perUnitPattern": "{0}/m³"
          },
          "volume-cubic-centimeter": {
            "displayName": "sentímetru kúbiku",
            "unitPattern-count-other": "{0} sentímetru kúbiku",
            "perUnitPattern": "{0}/cm³"
          },
          "volume-cubic-mile": {
            "displayName": "milha kúbiku",
            "unitPattern-count-other": "{0} milha kúbiku"
          },
          "volume-cubic-yard": {
            "displayName": "jarda kúbiku",
            "unitPattern-count-other": "{0} jarda kúbiku"
          },
          "volume-cubic-foot": {
            "displayName": "pé kúbiku",
            "unitPattern-count-other": "{0} pé kúbiku"
          },
          "volume-cubic-inch": {
            "displayName": "pulegada kúbiku",
            "unitPattern-count-other": "{0} pulegada kúbiku"
          },
          "volume-megaliter": {
            "displayName": "megalitru",
            "unitPattern-count-other": "{0} megalitru"
          },
          "volume-hectoliter": {
            "displayName": "ektolitru",
            "unitPattern-count-other": "{0} ektolitru"
          },
          "volume-liter": {
            "displayName": "litru",
            "unitPattern-count-other": "{0} litru",
            "perUnitPattern": "{0}/l"
          },
          "volume-deciliter": {
            "displayName": "desilitru",
            "unitPattern-count-other": "{0} desilitru"
          },
          "volume-centiliter": {
            "displayName": "sentilitru",
            "unitPattern-count-other": "{0} sentilitru"
          },
          "volume-milliliter": {
            "displayName": "mililitru",
            "unitPattern-count-other": "{0} mililitru"
          },
          "volume-pint-metric": {
            "displayName": "mpt",
            "unitPattern-count-other": "{0} mpt"
          },
          "volume-cup-metric": {
            "displayName": "mcup",
            "unitPattern-count-other": "{0} mc"
          },
          "volume-acre-foot": {
            "displayName": "ákri-pé",
            "unitPattern-count-other": "{0} ákri-pé"
          },
          "volume-bushel": {
            "displayName": "bu",
            "unitPattern-count-other": "{0} bu"
          },
          "volume-gallon": {
            "displayName": "galãu",
            "unitPattern-count-other": "{0} galãu",
            "perUnitPattern": "{0}/gal US"
          },
          "volume-gallon-imperial": {
            "displayName": "Imp. gal",
            "unitPattern-count-other": "{0} gal Imp.",
            "perUnitPattern": "{0}/gal Imp."
          },
          "volume-quart": {
            "displayName": "kuart",
            "unitPattern-count-other": "{0} kuart"
          },
          "volume-pint": {
            "displayName": "pint",
            "unitPattern-count-other": "{0} pint"
          },
          "volume-cup": {
            "displayName": "xávina",
            "unitPattern-count-other": "{0} xávina"
          },
          "volume-fluid-ounce": {
            "displayName": "ónsa fluídu",
            "unitPattern-count-other": "{0} ónsa fluídu"
          },
          "volume-tablespoon": {
            "displayName": "kudjer di sopa",
            "unitPattern-count-other": "{0} kudjer di sopa"
          },
          "volume-teaspoon": {
            "displayName": "kudjer di xá",
            "unitPattern-count-other": "{0} kudjer di xá"
          },
          "coordinateUnit": {
            "east": "{0}E",
            "north": "{0}N",
            "south": "{0}S",
            "west": "{0}W"
          }
        },
        "short": {
          "per": {
            "compoundUnitPattern": "{0}/{1}"
          },
          "acceleration-g-force": {
            "displayName": "G",
            "unitPattern-count-other": "{0} G"
          },
          "acceleration-meter-per-second-squared": {
            "displayName": "m/s²",
            "unitPattern-count-other": "{0} m/s²"
          },
          "angle-revolution": {
            "displayName": "rev",
            "unitPattern-count-other": "{0} rev"
          },
          "angle-radian": {
            "displayName": "rad",
            "unitPattern-count-other": "{0} rad"
          },
          "angle-degree": {
            "displayName": "grau",
            "unitPattern-count-other": "{0}°"
          },
          "angle-arc-minute": {
            "displayName": "arcmin",
            "unitPattern-count-other": "{0}′"
          },
          "angle-arc-second": {
            "displayName": "arcsec",
            "unitPattern-count-other": "{0}″"
          },
          "area-square-kilometer": {
            "displayName": "km²",
            "unitPattern-count-other": "{0} km²"
          },
          "area-hectare": {
            "displayName": "ha",
            "unitPattern-count-other": "{0} ha"
          },
          "area-square-meter": {
            "displayName": "m²",
            "unitPattern-count-other": "{0} m²",
            "perUnitPattern": "{0}/m²"
          },
          "area-square-centimeter": {
            "displayName": "cm²",
            "unitPattern-count-other": "{0} cm²",
            "perUnitPattern": "{0}/cm²"
          },
          "area-square-mile": {
            "displayName": "mi²",
            "unitPattern-count-other": "{0} mi²"
          },
          "area-acre": {
            "displayName": "ac",
            "unitPattern-count-other": "{0} ac"
          },
          "area-square-yard": {
            "displayName": "yd²",
            "unitPattern-count-other": "{0} yd²"
          },
          "area-square-foot": {
            "displayName": "ft²",
            "unitPattern-count-other": "{0} ft²"
          },
          "area-square-inch": {
            "displayName": "in²",
            "unitPattern-count-other": "{0} in²",
            "perUnitPattern": "{0}/in²"
          },
          "concentr-karat": {
            "displayName": "kt",
            "unitPattern-count-other": "{0} kt"
          },
          "concentr-milligram-per-deciliter": {
            "displayName": "mg/dL",
            "unitPattern-count-other": "{0} mg/dL"
          },
          "concentr-millimole-per-liter": {
            "displayName": "mmol/L",
            "unitPattern-count-other": "{0} mmol/L"
          },
          "concentr-part-per-million": {
            "displayName": "ppm",
            "unitPattern-count-other": "{0} ppm"
          },
          "consumption-liter-per-kilometer": {
            "displayName": "l/km",
            "unitPattern-count-other": "{0} l/km"
          },
          "consumption-liter-per-100kilometers": {
            "displayName": "L/100km",
            "unitPattern-count-other": "{0} L/100km"
          },
          "consumption-mile-per-gallon": {
            "displayName": "mpg",
            "unitPattern-count-other": "{0} mpg"
          },
          "consumption-mile-per-gallon-imperial": {
            "displayName": "mpg Imp.",
            "unitPattern-count-other": "{0} mpg Imp."
          },
          "digital-terabyte": {
            "displayName": "TB",
            "unitPattern-count-other": "{0} TB"
          },
          "digital-terabit": {
            "displayName": "Tb",
            "unitPattern-count-other": "{0} Tb"
          },
          "digital-gigabyte": {
            "displayName": "GB",
            "unitPattern-count-other": "{0} GB"
          },
          "digital-gigabit": {
            "displayName": "Gb",
            "unitPattern-count-other": "{0} Gb"
          },
          "digital-megabyte": {
            "displayName": "MB",
            "unitPattern-count-other": "{0} MB"
          },
          "digital-megabit": {
            "displayName": "Mb",
            "unitPattern-count-other": "{0} Mb"
          },
          "digital-kilobyte": {
            "displayName": "KB",
            "unitPattern-count-other": "{0} KB"
          },
          "digital-kilobit": {
            "displayName": "Kb",
            "unitPattern-count-other": "{0} Kb"
          },
          "digital-byte": {
            "displayName": "B",
            "unitPattern-count-other": "{0} B"
          },
          "digital-bit": {
            "displayName": "b",
            "unitPattern-count-other": "{0} b"
          },
          "duration-century": {
            "displayName": "c",
            "unitPattern-count-other": "{0} c"
          },
          "duration-year": {
            "displayName": "anu",
            "unitPattern-count-other": "{0} anu",
            "perUnitPattern": "{0}/y"
          },
          "duration-month": {
            "displayName": "mes",
            "unitPattern-count-other": "{0} mes",
            "perUnitPattern": "{0}/m"
          },
          "duration-week": {
            "displayName": "sim.",
            "unitPattern-count-other": "{0} sim.",
            "perUnitPattern": "{0}/w"
          },
          "duration-day": {
            "displayName": "dia",
            "unitPattern-count-other": "{0} dia",
            "perUnitPattern": "{0}/d"
          },
          "duration-hour": {
            "displayName": "ora",
            "unitPattern-count-other": "{0} h",
            "perUnitPattern": "{0}/h"
          },
          "duration-minute": {
            "displayName": "min.",
            "unitPattern-count-other": "{0} min.",
            "perUnitPattern": "{0}/min"
          },
          "duration-second": {
            "displayName": "sig.",
            "unitPattern-count-other": "{0} sig.",
            "perUnitPattern": "{0}/s"
          },
          "duration-millisecond": {
            "displayName": "ms",
            "unitPattern-count-other": "{0} ms"
          },
          "duration-microsecond": {
            "displayName": "μs",
            "unitPattern-count-other": "{0} μs"
          },
          "duration-nanosecond": {
            "displayName": "ns",
            "unitPattern-count-other": "{0} ns"
          },
          "electric-ampere": {
            "displayName": "amp",
            "unitPattern-count-other": "{0} A"
          },
          "electric-milliampere": {
            "displayName": "mA",
            "unitPattern-count-other": "{0} mA"
          },
          "electric-ohm": {
            "displayName": "ohm",
            "unitPattern-count-other": "{0} Ω"
          },
          "electric-volt": {
            "displayName": "volt",
            "unitPattern-count-other": "{0} V"
          },
          "energy-kilocalorie": {
            "displayName": "kcal",
            "unitPattern-count-other": "{0} kcal"
          },
          "energy-calorie": {
            "displayName": "cal",
            "unitPattern-count-other": "{0} cal"
          },
          "energy-foodcalorie": {
            "displayName": "Cal",
            "unitPattern-count-other": "{0} Cal"
          },
          "energy-kilojoule": {
            "displayName": "kJ",
            "unitPattern-count-other": "{0} kJ"
          },
          "energy-joule": {
            "displayName": "joule",
            "unitPattern-count-other": "{0} J"
          },
          "energy-kilowatt-hour": {
            "displayName": "kWh",
            "unitPattern-count-other": "{0} kWh"
          },
          "frequency-gigahertz": {
            "displayName": "GHz",
            "unitPattern-count-other": "{0} GHz"
          },
          "frequency-megahertz": {
            "displayName": "MHz",
            "unitPattern-count-other": "{0} MHz"
          },
          "frequency-kilohertz": {
            "displayName": "kHz",
            "unitPattern-count-other": "{0} kHz"
          },
          "frequency-hertz": {
            "displayName": "Hz",
            "unitPattern-count-other": "{0} Hz"
          },
          "length-kilometer": {
            "displayName": "km",
            "unitPattern-count-other": "{0} km",
            "perUnitPattern": "{0}/km"
          },
          "length-meter": {
            "displayName": "m",
            "unitPattern-count-other": "{0} m",
            "perUnitPattern": "{0}/m"
          },
          "length-decimeter": {
            "displayName": "dm",
            "unitPattern-count-other": "{0} dm"
          },
          "length-centimeter": {
            "displayName": "cm",
            "unitPattern-count-other": "{0} cm",
            "perUnitPattern": "{0}/cm"
          },
          "length-millimeter": {
            "displayName": "mm",
            "unitPattern-count-other": "{0} mm"
          },
          "length-micrometer": {
            "displayName": "µm",
            "unitPattern-count-other": "{0} µm"
          },
          "length-nanometer": {
            "displayName": "nm",
            "unitPattern-count-other": "{0} nm"
          },
          "length-picometer": {
            "displayName": "pm",
            "unitPattern-count-other": "{0} pm"
          },
          "length-mile": {
            "displayName": "mi",
            "unitPattern-count-other": "{0} mi"
          },
          "length-yard": {
            "displayName": "yd",
            "unitPattern-count-other": "{0} yd"
          },
          "length-foot": {
            "displayName": "pé",
            "unitPattern-count-other": "{0} pé",
            "perUnitPattern": "{0}/ft"
          },
          "length-inch": {
            "displayName": "in",
            "unitPattern-count-other": "{0} in",
            "perUnitPattern": "{0}/in"
          },
          "length-parsec": {
            "displayName": "pc",
            "unitPattern-count-other": "{0} pc"
          },
          "length-light-year": {
            "displayName": "anu-lus",
            "unitPattern-count-other": "{0} anu-lus"
          },
          "length-astronomical-unit": {
            "displayName": "ua",
            "unitPattern-count-other": "{0} ua"
          },
          "length-furlong": {
            "displayName": "fur",
            "unitPattern-count-other": "{0} fur"
          },
          "length-fathom": {
            "displayName": "fm",
            "unitPattern-count-other": "{0} fm"
          },
          "length-nautical-mile": {
            "displayName": "nmi",
            "unitPattern-count-other": "{0} nmi"
          },
          "length-mile-scandinavian": {
            "displayName": "smi",
            "unitPattern-count-other": "{0} smi"
          },
          "light-lux": {
            "displayName": "lux",
            "unitPattern-count-other": "{0} lx"
          },
          "mass-metric-ton": {
            "displayName": "t",
            "unitPattern-count-other": "{0} t"
          },
          "mass-kilogram": {
            "displayName": "kg",
            "unitPattern-count-other": "{0} kg",
            "perUnitPattern": "{0}/kg"
          },
          "mass-gram": {
            "displayName": "gram",
            "unitPattern-count-other": "{0} g",
            "perUnitPattern": "{0}/g"
          },
          "mass-milligram": {
            "displayName": "mg",
            "unitPattern-count-other": "{0} mg"
          },
          "mass-microgram": {
            "displayName": "µg",
            "unitPattern-count-other": "{0} µg"
          },
          "mass-ton": {
            "displayName": "tn",
            "unitPattern-count-other": "{0} tn"
          },
          "mass-stone": {
            "displayName": "st",
            "unitPattern-count-other": "{0} st"
          },
          "mass-pound": {
            "displayName": "lb",
            "unitPattern-count-other": "{0} lb",
            "perUnitPattern": "{0}/lb"
          },
          "mass-ounce": {
            "displayName": "oz",
            "unitPattern-count-other": "{0} oz",
            "perUnitPattern": "{0}/oz"
          },
          "mass-ounce-troy": {
            "displayName": "oz t",
            "unitPattern-count-other": "{0} oz t"
          },
          "mass-carat": {
            "displayName": "CD",
            "unitPattern-count-other": "{0} CD"
          },
          "power-gigawatt": {
            "displayName": "GW",
            "unitPattern-count-other": "{0} GW"
          },
          "power-megawatt": {
            "displayName": "MW",
            "unitPattern-count-other": "{0} MW"
          },
          "power-kilowatt": {
            "displayName": "kW",
            "unitPattern-count-other": "{0} kW"
          },
          "power-watt": {
            "displayName": "watt",
            "unitPattern-count-other": "{0} W"
          },
          "power-milliwatt": {
            "displayName": "mW",
            "unitPattern-count-other": "{0} mW"
          },
          "power-horsepower": {
            "displayName": "hp",
            "unitPattern-count-other": "{0} hp"
          },
          "pressure-hectopascal": {
            "displayName": "hPa",
            "unitPattern-count-other": "{0} hPa"
          },
          "pressure-millimeter-of-mercury": {
            "displayName": "mm Hg",
            "unitPattern-count-other": "{0} mm Hg"
          },
          "pressure-pound-per-square-inch": {
            "displayName": "psi",
            "unitPattern-count-other": "{0} psi"
          },
          "pressure-inch-hg": {
            "displayName": "inHg",
            "unitPattern-count-other": "{0} inHg"
          },
          "pressure-millibar": {
            "displayName": "mbar",
            "unitPattern-count-other": "{0} mbar"
          },
          "speed-kilometer-per-hour": {
            "displayName": "km/h",
            "unitPattern-count-other": "{0} km/h"
          },
          "speed-meter-per-second": {
            "displayName": "m/s",
            "unitPattern-count-other": "{0} m/s"
          },
          "speed-mile-per-hour": {
            "displayName": "mi/h",
            "unitPattern-count-other": "{0} mi/h"
          },
          "speed-knot": {
            "displayName": "kn",
            "unitPattern-count-other": "{0} kn"
          },
          "temperature-generic": {
            "displayName": "°",
            "unitPattern-count-other": "{0}°"
          },
          "temperature-celsius": {
            "displayName": "°C",
            "unitPattern-count-other": "{0}°C"
          },
          "temperature-fahrenheit": {
            "displayName": "°F",
            "unitPattern-count-other": "{0}°F"
          },
          "temperature-kelvin": {
            "displayName": "K",
            "unitPattern-count-other": "{0} K"
          },
          "volume-cubic-kilometer": {
            "displayName": "km³",
            "unitPattern-count-other": "{0} km³"
          },
          "volume-cubic-meter": {
            "displayName": "m³",
            "unitPattern-count-other": "{0} m³",
            "perUnitPattern": "{0}/m³"
          },
          "volume-cubic-centimeter": {
            "displayName": "cm³",
            "unitPattern-count-other": "{0} cm³",
            "perUnitPattern": "{0}/cm³"
          },
          "volume-cubic-mile": {
            "displayName": "mi³",
            "unitPattern-count-other": "{0} mi³"
          },
          "volume-cubic-yard": {
            "displayName": "yd³",
            "unitPattern-count-other": "{0} yd³"
          },
          "volume-cubic-foot": {
            "displayName": "ft³",
            "unitPattern-count-other": "{0} ft³"
          },
          "volume-cubic-inch": {
            "displayName": "in³",
            "unitPattern-count-other": "{0} in³"
          },
          "volume-megaliter": {
            "displayName": "Ml",
            "unitPattern-count-other": "{0} Ml"
          },
          "volume-hectoliter": {
            "displayName": "hl",
            "unitPattern-count-other": "{0} hl"
          },
          "volume-liter": {
            "displayName": "l",
            "unitPattern-count-other": "{0} l",
            "perUnitPattern": "{0}/l"
          },
          "volume-deciliter": {
            "displayName": "dl",
            "unitPattern-count-other": "{0} dl"
          },
          "volume-centiliter": {
            "displayName": "cl",
            "unitPattern-count-other": "{0} cl"
          },
          "volume-milliliter": {
            "displayName": "ml",
            "unitPattern-count-other": "{0} ml"
          },
          "volume-pint-metric": {
            "displayName": "mpt",
            "unitPattern-count-other": "{0} mpt"
          },
          "volume-cup-metric": {
            "displayName": "mcup",
            "unitPattern-count-other": "{0} mc"
          },
          "volume-acre-foot": {
            "displayName": "ac ft",
            "unitPattern-count-other": "{0} ac ft"
          },
          "volume-bushel": {
            "displayName": "bu",
            "unitPattern-count-other": "{0} bu"
          },
          "volume-gallon": {
            "displayName": "gal",
            "unitPattern-count-other": "{0} gal",
            "perUnitPattern": "{0}/gal US"
          },
          "volume-gallon-imperial": {
            "displayName": "Imp. gal",
            "unitPattern-count-other": "{0} gal Imp.",
            "perUnitPattern": "{0}/gal Imp."
          },
          "volume-quart": {
            "displayName": "qt",
            "unitPattern-count-other": "{0} qt"
          },
          "volume-pint": {
            "displayName": "pt",
            "unitPattern-count-other": "{0} pt"
          },
          "volume-cup": {
            "displayName": "xáv.",
            "unitPattern-count-other": "{0} xáv."
          },
          "volume-fluid-ounce": {
            "displayName": "fl oz",
            "unitPattern-count-other": "{0} fl oz"
          },
          "volume-tablespoon": {
            "displayName": "k.sp.",
            "unitPattern-count-other": "{0} k.sp."
          },
          "volume-teaspoon": {
            "displayName": "k.xá",
            "unitPattern-count-other": "{0} k.xá"
          },
          "coordinateUnit": {
            "east": "{0}E",
            "north": "{0}N",
            "south": "{0}S",
            "west": "{0}W"
          }
        },
        "narrow": {
          "per": {
            "compoundUnitPattern": "{0}/{1}"
          },
          "acceleration-g-force": {
            "displayName": "G",
            "unitPattern-count-other": "{0} G"
          },
          "acceleration-meter-per-second-squared": {
            "displayName": "m/s²",
            "unitPattern-count-other": "{0} m/s²"
          },
          "angle-revolution": {
            "displayName": "rev",
            "unitPattern-count-other": "{0} rev"
          },
          "angle-radian": {
            "displayName": "rad",
            "unitPattern-count-other": "{0} rad"
          },
          "angle-degree": {
            "displayName": "grau",
            "unitPattern-count-other": "{0}°"
          },
          "angle-arc-minute": {
            "displayName": "arcmin",
            "unitPattern-count-other": "{0}′"
          },
          "angle-arc-second": {
            "displayName": "arcsec",
            "unitPattern-count-other": "{0}″"
          },
          "area-square-kilometer": {
            "displayName": "km²",
            "unitPattern-count-other": "{0} km²"
          },
          "area-hectare": {
            "displayName": "ha",
            "unitPattern-count-other": "{0} ha"
          },
          "area-square-meter": {
            "displayName": "m²",
            "unitPattern-count-other": "{0} m²",
            "perUnitPattern": "{0}/m²"
          },
          "area-square-centimeter": {
            "displayName": "cm²",
            "unitPattern-count-other": "{0} cm²",
            "perUnitPattern": "{0}/cm²"
          },
          "area-square-mile": {
            "displayName": "mi²",
            "unitPattern-count-other": "{0} mi²"
          },
          "area-acre": {
            "displayName": "ac",
            "unitPattern-count-other": "{0} ac"
          },
          "area-square-yard": {
            "displayName": "yd²",
            "unitPattern-count-other": "{0} yd²"
          },
          "area-square-foot": {
            "displayName": "ft²",
            "unitPattern-count-other": "{0} ft²"
          },
          "area-square-inch": {
            "displayName": "in²",
            "unitPattern-count-other": "{0} in²",
            "perUnitPattern": "{0}/in²"
          },
          "concentr-karat": {
            "displayName": "kt",
            "unitPattern-count-other": "{0} kt"
          },
          "concentr-milligram-per-deciliter": {
            "displayName": "mg/dL",
            "unitPattern-count-other": "{0} mg/dL"
          },
          "concentr-millimole-per-liter": {
            "displayName": "mmol/L",
            "unitPattern-count-other": "{0} mmol/L"
          },
          "concentr-part-per-million": {
            "displayName": "ppm",
            "unitPattern-count-other": "{0} ppm"
          },
          "consumption-liter-per-kilometer": {
            "displayName": "l/km",
            "unitPattern-count-other": "{0} l/km"
          },
          "consumption-liter-per-100kilometers": {
            "displayName": "L/100km",
            "unitPattern-count-other": "{0} L/100km"
          },
          "consumption-mile-per-gallon": {
            "displayName": "mpg",
            "unitPattern-count-other": "{0} mpg"
          },
          "consumption-mile-per-gallon-imperial": {
            "displayName": "mpg Imp.",
            "unitPattern-count-other": "{0} mpg Imp."
          },
          "digital-terabyte": {
            "displayName": "TB",
            "unitPattern-count-other": "{0} TB"
          },
          "digital-terabit": {
            "displayName": "Tb",
            "unitPattern-count-other": "{0} Tb"
          },
          "digital-gigabyte": {
            "displayName": "GB",
            "unitPattern-count-other": "{0} GB"
          },
          "digital-gigabit": {
            "displayName": "Gb",
            "unitPattern-count-other": "{0} Gb"
          },
          "digital-megabyte": {
            "displayName": "MB",
            "unitPattern-count-other": "{0} MB"
          },
          "digital-megabit": {
            "displayName": "Mb",
            "unitPattern-count-other": "{0} Mb"
          },
          "digital-kilobyte": {
            "displayName": "KB",
            "unitPattern-count-other": "{0} KB"
          },
          "digital-kilobit": {
            "displayName": "Kb",
            "unitPattern-count-other": "{0} Kb"
          },
          "digital-byte": {
            "displayName": "B",
            "unitPattern-count-other": "{0} B"
          },
          "digital-bit": {
            "displayName": "b",
            "unitPattern-count-other": "{0} b"
          },
          "duration-century": {
            "displayName": "c",
            "unitPattern-count-other": "{0} c"
          },
          "duration-year": {
            "displayName": "anu",
            "unitPattern-count-other": "{0} anu",
            "perUnitPattern": "{0}/y"
          },
          "duration-month": {
            "displayName": "mes",
            "unitPattern-count-other": "{0} mes",
            "perUnitPattern": "{0}/m"
          },
          "duration-week": {
            "displayName": "sim.",
            "unitPattern-count-other": "{0} sim.",
            "perUnitPattern": "{0}/w"
          },
          "duration-day": {
            "displayName": "dia",
            "unitPattern-count-other": "{0} dia",
            "perUnitPattern": "{0}/d"
          },
          "duration-hour": {
            "displayName": "ora",
            "unitPattern-count-other": "{0} h",
            "perUnitPattern": "{0}/h"
          },
          "duration-minute": {
            "displayName": "min.",
            "unitPattern-count-other": "{0} min.",
            "perUnitPattern": "{0}/min"
          },
          "duration-second": {
            "displayName": "sig.",
            "unitPattern-count-other": "{0} s",
            "perUnitPattern": "{0}/s"
          },
          "duration-millisecond": {
            "displayName": "ms",
            "unitPattern-count-other": "{0} ms"
          },
          "duration-microsecond": {
            "displayName": "μs",
            "unitPattern-count-other": "{0} μs"
          },
          "duration-nanosecond": {
            "displayName": "ns",
            "unitPattern-count-other": "{0} ns"
          },
          "electric-ampere": {
            "displayName": "amp",
            "unitPattern-count-other": "{0} A"
          },
          "electric-milliampere": {
            "displayName": "mA",
            "unitPattern-count-other": "{0} mA"
          },
          "electric-ohm": {
            "displayName": "ohm",
            "unitPattern-count-other": "{0} Ω"
          },
          "electric-volt": {
            "displayName": "volt",
            "unitPattern-count-other": "{0} V"
          },
          "energy-kilocalorie": {
            "displayName": "kcal",
            "unitPattern-count-other": "{0} kcal"
          },
          "energy-calorie": {
            "displayName": "cal",
            "unitPattern-count-other": "{0} cal"
          },
          "energy-foodcalorie": {
            "displayName": "Cal",
            "unitPattern-count-other": "{0} Cal"
          },
          "energy-kilojoule": {
            "displayName": "kJ",
            "unitPattern-count-other": "{0} kJ"
          },
          "energy-joule": {
            "displayName": "joule",
            "unitPattern-count-other": "{0} J"
          },
          "energy-kilowatt-hour": {
            "displayName": "kWh",
            "unitPattern-count-other": "{0} kWh"
          },
          "frequency-gigahertz": {
            "displayName": "GHz",
            "unitPattern-count-other": "{0} GHz"
          },
          "frequency-megahertz": {
            "displayName": "MHz",
            "unitPattern-count-other": "{0} MHz"
          },
          "frequency-kilohertz": {
            "displayName": "kHz",
            "unitPattern-count-other": "{0} kHz"
          },
          "frequency-hertz": {
            "displayName": "Hz",
            "unitPattern-count-other": "{0} Hz"
          },
          "length-kilometer": {
            "displayName": "km",
            "unitPattern-count-other": "{0} km",
            "perUnitPattern": "{0}/km"
          },
          "length-meter": {
            "displayName": "m",
            "unitPattern-count-other": "{0} m",
            "perUnitPattern": "{0}/m"
          },
          "length-decimeter": {
            "displayName": "dm",
            "unitPattern-count-other": "{0} dm"
          },
          "length-centimeter": {
            "displayName": "cm",
            "unitPattern-count-other": "{0} cm",
            "perUnitPattern": "{0}/cm"
          },
          "length-millimeter": {
            "displayName": "mm",
            "unitPattern-count-other": "{0} mm"
          },
          "length-micrometer": {
            "displayName": "µm",
            "unitPattern-count-other": "{0} µm"
          },
          "length-nanometer": {
            "displayName": "nm",
            "unitPattern-count-other": "{0} nm"
          },
          "length-picometer": {
            "displayName": "pm",
            "unitPattern-count-other": "{0} pm"
          },
          "length-mile": {
            "displayName": "mi",
            "unitPattern-count-other": "{0} mi"
          },
          "length-yard": {
            "displayName": "yd",
            "unitPattern-count-other": "{0} yd"
          },
          "length-foot": {
            "displayName": "pé",
            "unitPattern-count-other": "{0} pé",
            "perUnitPattern": "{0}/ft"
          },
          "length-inch": {
            "displayName": "in",
            "unitPattern-count-other": "{0} in",
            "perUnitPattern": "{0}/in"
          },
          "length-parsec": {
            "displayName": "pc",
            "unitPattern-count-other": "{0} pc"
          },
          "length-light-year": {
            "displayName": "anu-lus",
            "unitPattern-count-other": "{0} anu-lus"
          },
          "length-astronomical-unit": {
            "displayName": "ua",
            "unitPattern-count-other": "{0} ua"
          },
          "length-furlong": {
            "displayName": "fur",
            "unitPattern-count-other": "{0} fur"
          },
          "length-fathom": {
            "displayName": "fm",
            "unitPattern-count-other": "{0} fm"
          },
          "length-nautical-mile": {
            "displayName": "nmi",
            "unitPattern-count-other": "{0} nmi"
          },
          "length-mile-scandinavian": {
            "displayName": "smi",
            "unitPattern-count-other": "{0} smi"
          },
          "light-lux": {
            "displayName": "lux",
            "unitPattern-count-other": "{0} lx"
          },
          "mass-metric-ton": {
            "displayName": "t",
            "unitPattern-count-other": "{0} t"
          },
          "mass-kilogram": {
            "displayName": "kg",
            "unitPattern-count-other": "{0} kg",
            "perUnitPattern": "{0}/kg"
          },
          "mass-gram": {
            "displayName": "gram",
            "unitPattern-count-other": "{0} g",
            "perUnitPattern": "{0}/g"
          },
          "mass-milligram": {
            "displayName": "mg",
            "unitPattern-count-other": "{0} mg"
          },
          "mass-microgram": {
            "displayName": "µg",
            "unitPattern-count-other": "{0} µg"
          },
          "mass-ton": {
            "displayName": "tn",
            "unitPattern-count-other": "{0} tn"
          },
          "mass-stone": {
            "displayName": "st",
            "unitPattern-count-other": "{0} st"
          },
          "mass-pound": {
            "displayName": "lb",
            "unitPattern-count-other": "{0} lb",
            "perUnitPattern": "{0}/lb"
          },
          "mass-ounce": {
            "displayName": "oz",
            "unitPattern-count-other": "{0} oz",
            "perUnitPattern": "{0}/oz"
          },
          "mass-ounce-troy": {
            "displayName": "oz t",
            "unitPattern-count-other": "{0} oz t"
          },
          "mass-carat": {
            "displayName": "CD",
            "unitPattern-count-other": "{0} CD"
          },
          "power-gigawatt": {
            "displayName": "GW",
            "unitPattern-count-other": "{0} GW"
          },
          "power-megawatt": {
            "displayName": "MW",
            "unitPattern-count-other": "{0} MW"
          },
          "power-kilowatt": {
            "displayName": "kW",
            "unitPattern-count-other": "{0} kW"
          },
          "power-watt": {
            "displayName": "watt",
            "unitPattern-count-other": "{0} W"
          },
          "power-milliwatt": {
            "displayName": "mW",
            "unitPattern-count-other": "{0} mW"
          },
          "power-horsepower": {
            "displayName": "hp",
            "unitPattern-count-other": "{0} hp"
          },
          "pressure-hectopascal": {
            "displayName": "hPa",
            "unitPattern-count-other": "{0} hPa"
          },
          "pressure-millimeter-of-mercury": {
            "displayName": "mm Hg",
            "unitPattern-count-other": "{0} mm Hg"
          },
          "pressure-pound-per-square-inch": {
            "displayName": "psi",
            "unitPattern-count-other": "{0} psi"
          },
          "pressure-inch-hg": {
            "displayName": "inHg",
            "unitPattern-count-other": "{0} inHg"
          },
          "pressure-millibar": {
            "displayName": "mbar",
            "unitPattern-count-other": "{0} mbar"
          },
          "speed-kilometer-per-hour": {
            "displayName": "km/h",
            "unitPattern-count-other": "{0} km/h"
          },
          "speed-meter-per-second": {
            "displayName": "m/s",
            "unitPattern-count-other": "{0} m/s"
          },
          "speed-mile-per-hour": {
            "displayName": "mi/h",
            "unitPattern-count-other": "{0} mi/h"
          },
          "speed-knot": {
            "displayName": "kn",
            "unitPattern-count-other": "{0} kn"
          },
          "temperature-generic": {
            "displayName": "°",
            "unitPattern-count-other": "{0}°"
          },
          "temperature-celsius": {
            "displayName": "°C",
            "unitPattern-count-other": "{0}°C"
          },
          "temperature-fahrenheit": {
            "displayName": "°F",
            "unitPattern-count-other": "{0}°F"
          },
          "temperature-kelvin": {
            "displayName": "K",
            "unitPattern-count-other": "{0} K"
          },
          "volume-cubic-kilometer": {
            "displayName": "km³",
            "unitPattern-count-other": "{0} km³"
          },
          "volume-cubic-meter": {
            "displayName": "m³",
            "unitPattern-count-other": "{0} m³",
            "perUnitPattern": "{0}/m³"
          },
          "volume-cubic-centimeter": {
            "displayName": "cm³",
            "unitPattern-count-other": "{0} cm³",
            "perUnitPattern": "{0}/cm³"
          },
          "volume-cubic-mile": {
            "displayName": "mi³",
            "unitPattern-count-other": "{0} mi³"
          },
          "volume-cubic-yard": {
            "displayName": "yd³",
            "unitPattern-count-other": "{0} yd³"
          },
          "volume-cubic-foot": {
            "displayName": "ft³",
            "unitPattern-count-other": "{0} ft³"
          },
          "volume-cubic-inch": {
            "displayName": "in³",
            "unitPattern-count-other": "{0} in³"
          },
          "volume-megaliter": {
            "displayName": "Ml",
            "unitPattern-count-other": "{0} Ml"
          },
          "volume-hectoliter": {
            "displayName": "hl",
            "unitPattern-count-other": "{0} hl"
          },
          "volume-liter": {
            "displayName": "l",
            "unitPattern-count-other": "{0} l",
            "perUnitPattern": "{0}/l"
          },
          "volume-deciliter": {
            "displayName": "dl",
            "unitPattern-count-other": "{0} dl"
          },
          "volume-centiliter": {
            "displayName": "cl",
            "unitPattern-count-other": "{0} cl"
          },
          "volume-milliliter": {
            "displayName": "ml",
            "unitPattern-count-other": "{0} ml"
          },
          "volume-pint-metric": {
            "displayName": "mpt",
            "unitPattern-count-other": "{0} mpt"
          },
          "volume-cup-metric": {
            "displayName": "mcup",
            "unitPattern-count-other": "{0} mc"
          },
          "volume-acre-foot": {
            "displayName": "ac ft",
            "unitPattern-count-other": "{0} ac ft"
          },
          "volume-bushel": {
            "displayName": "bu",
            "unitPattern-count-other": "{0} bu"
          },
          "volume-gallon": {
            "displayName": "gal",
            "unitPattern-count-other": "{0} gal",
            "perUnitPattern": "{0}/gal US"
          },
          "volume-gallon-imperial": {
            "displayName": "Imp. gal",
            "unitPattern-count-other": "{0} gal Imp.",
            "perUnitPattern": "{0}/gal Imp."
          },
          "volume-quart": {
            "displayName": "qt",
            "unitPattern-count-other": "{0} qt"
          },
          "volume-pint": {
            "displayName": "pt",
            "unitPattern-count-other": "{0} pt"
          },
          "volume-cup": {
            "displayName": "xáv.",
            "unitPattern-count-other": "{0} xáv."
          },
          "volume-fluid-ounce": {
            "displayName": "fl oz",
            "unitPattern-count-other": "{0} fl oz"
          },
          "volume-tablespoon": {
            "displayName": "k.sp.",
            "unitPattern-count-other": "{0} k.sp."
          },
          "volume-teaspoon": {
            "displayName": "k.xá",
            "unitPattern-count-other": "{0} k.xá"
          },
          "coordinateUnit": {
            "east": "{0}E",
            "north": "{0}N",
            "south": "{0}S",
            "west": "{0}W"
          }
        },
        "durationUnit-type-hm": {
          "durationUnitPattern": "h:mm"
        },
        "durationUnit-type-hms": {
          "durationUnitPattern": "h:mm:ss"
        },
        "durationUnit-type-ms": {
          "durationUnitPattern": "m:ss"
        }
      }
    }
  }
}
