{
  "main": {
    "ur": {
      "identity": {
        "version": {
          "_number": "$Revision: 12311 $",
          "_cldrVersion": "29"
        },
        "language": "ur"
      },
      "localeDisplayNames": {
        "scripts": {
          "Adlm": "Adlm",
          "Aghb": "Aghb",
          "Ahom": "Ahom",
          "Arab": "عربی",
          "Arab-alt-variant": "فارسی عربی",
          "Armi": "Armi",
          "Armn": "آرمینیائی",
          "Avst": "Avst",
          "Bali": "Bali",
          "Bamu": "Bamu",
          "Bass": "Bass",
          "Batk": "Batk",
          "Beng": "بنگالی",
          "Bhks": "Bhks",
          "Bopo": "بوپوموفو",
          "Brah": "Brah",
          "Brai": "بریل",
          "Bugi": "Bugi",
          "Buhd": "Buhd",
          "Cakm": "Cakm",
          "Cans": "Cans",
          "Cari": "Cari",
          "Cham": "Cham",
          "Cher": "Cher",
          "Copt": "Copt",
          "Cprt": "Cprt",
          "Cyrl": "سیریلک",
          "Deva": "دیوناگری",
          "Dsrt": "Dsrt",
          "Dupl": "Dupl",
          "Egyp": "Egyp",
          "Elba": "Elba",
          "Ethi": "ایتھوپیائی",
          "Geor": "جارجیائی",
          "Glag": "Glag",
          "Goth": "Goth",
          "Gran": "Gran",
          "Grek": "یونانی",
          "Gujr": "گجراتی",
          "Guru": "گرمکھی",
          "Hanb": "Hanb",
          "Hang": "ہنگول",
          "Hani": "ہان",
          "Hano": "Hano",
          "Hans": "آسان",
          "Hans-alt-stand-alone": "آسان ہان",
          "Hant": "روایتی",
          "Hant-alt-stand-alone": "روایتی ہان",
          "Hatr": "Hatr",
          "Hebr": "عبرانی",
          "Hira": "ہیراگینا",
          "Hluw": "Hluw",
          "Hmng": "Hmng",
          "Hrkt": "Hrkt",
          "Hung": "Hung",
          "Ital": "Ital",
          "Jamo": "Jamo",
          "Java": "Java",
          "Jpan": "جاپانی",
          "Kali": "Kali",
          "Kana": "کٹاکانا",
          "Khar": "Khar",
          "Khmr": "خمیر",
          "Khoj": "Khoj",
          "Knda": "کنڑ",
          "Kore": "کوریائی",
          "Kthi": "Kthi",
          "Lana": "Lana",
          "Laoo": "لاؤ",
          "Latn": "لاطینی",
          "Lepc": "Lepc",
          "Limb": "Limb",
          "Lina": "Lina",
          "Linb": "Linb",
          "Lisu": "Lisu",
          "Lyci": "Lyci",
          "Lydi": "Lydi",
          "Mahj": "Mahj",
          "Mand": "Mand",
          "Mani": "Mani",
          "Marc": "Marc",
          "Mend": "Mend",
          "Merc": "Merc",
          "Mero": "Mero",
          "Mlym": "ملیالم",
          "Modi": "Modi",
          "Mong": "منگولیائی",
          "Mroo": "Mroo",
          "Mtei": "Mtei",
          "Mult": "Mult",
          "Mymr": "میانمار",
          "Narb": "Narb",
          "Nbat": "Nbat",
          "Newa": "Newa",
          "Nkoo": "Nkoo",
          "Ogam": "Ogam",
          "Olck": "Olck",
          "Orkh": "Orkh",
          "Orya": "اڑیہ",
          "Osge": "Osge",
          "Osma": "Osma",
          "Palm": "Palm",
          "Pauc": "Pauc",
          "Perm": "Perm",
          "Phag": "Phag",
          "Phli": "Phli",
          "Phlp": "Phlp",
          "Phnx": "Phnx",
          "Plrd": "Plrd",
          "Prti": "Prti",
          "Qaaa": "Qaaa",
          "Qaab": "Qaab",
          "Qaac": "Qaac",
          "Qaad": "Qaad",
          "Qaae": "Qaae",
          "Qaaf": "Qaaf",
          "Qaag": "Qaag",
          "Qaah": "Qaah",
          "Qaaj": "Qaaj",
          "Qaak": "Qaak",
          "Qaal": "Qaal",
          "Qaam": "Qaam",
          "Qaan": "Qaan",
          "Qaao": "Qaao",
          "Qaap": "Qaap",
          "Qaaq": "Qaaq",
          "Qaar": "Qaar",
          "Qaas": "Qaas",
          "Qaat": "Qaat",
          "Qaau": "Qaau",
          "Qaav": "Qaav",
          "Qaaw": "Qaaw",
          "Qaax": "Qaax",
          "Qaay": "Qaay",
          "Qaaz": "Qaaz",
          "Qaba": "Qaba",
          "Qabb": "Qabb",
          "Qabc": "Qabc",
          "Qabd": "Qabd",
          "Qabe": "Qabe",
          "Qabf": "Qabf",
          "Qabg": "Qabg",
          "Qabh": "Qabh",
          "Qabi": "Qabi",
          "Qabj": "Qabj",
          "Qabk": "Qabk",
          "Qabl": "Qabl",
          "Qabm": "Qabm",
          "Qabn": "Qabn",
          "Qabo": "Qabo",
          "Qabp": "Qabp",
          "Qabq": "Qabq",
          "Qabr": "Qabr",
          "Qabs": "Qabs",
          "Qabt": "Qabt",
          "Qabu": "Qabu",
          "Qabv": "Qabv",
          "Qabw": "Qabw",
          "Qabx": "Qabx",
          "Rjng": "Rjng",
          "Runr": "Runr",
          "Samr": "Samr",
          "Sarb": "Sarb",
          "Saur": "Saur",
          "Sgnw": "Sgnw",
          "Shaw": "Shaw",
          "Shrd": "Shrd",
          "Sidd": "Sidd",
          "Sind": "Sind",
          "Sinh": "سنہالا",
          "Sora": "Sora",
          "Sund": "Sund",
          "Sylo": "Sylo",
          "Syrc": "Syrc",
          "Tagb": "Tagb",
          "Takr": "Takr",
          "Tale": "Tale",
          "Talu": "Talu",
          "Taml": "تمل",
          "Tang": "Tang",
          "Tavt": "Tavt",
          "Telu": "تیلگو",
          "Tfng": "Tfng",
          "Tglg": "Tglg",
          "Thaa": "تھانا",
          "Thai": "تھائی",
          "Tibt": "تبتی",
          "Tirh": "Tirh",
          "Ugar": "Ugar",
          "Vaii": "Vaii",
          "Wara": "Wara",
          "Xpeo": "Xpeo",
          "Xsux": "Xsux",
          "Yiii": "Yiii",
          "Zinh": "Zinh",
          "Zmth": "Zmth",
          "Zsye": "Zsye",
          "Zsym": "علامات",
          "Zxxx": "غیر تحریر شدہ",
          "Zyyy": "عام",
          "Zzzz": "نامعلوم رسم الخط"
        }
      }
    }
  }
}
